ykbio/__init__.py
ykbio/__pycache__/__init__.cpython-38.pyc
ykbio/io/__init__.py
ykbio/io/read.py
ykbio/io/write.py
ykbio/io/__pycache__/__init__.cpython-38.pyc
ykbio/io/__pycache__/read.cpython-38.pyc
ykbio/message/__init__.py
ykbio/message/exception.py
ykbio/message/__pycache__/__init__.cpython-38.pyc
ykbio/message/__pycache__/exception.cpython-38.pyc
ykbio/plot/__init__.py
ykbio/region/__init__.py
ykbio/region/extract.py
ykbio/region/filter.py
ykbio/region/intersect.py
ykbio/region/rmdup.py
ykbio/region/subtract.py
ykbio/stats/__init__.py
ykbio/stats/correlation_analysis.py
ykbio/utility/__init__.py
ykbio-1.0.1.dist-info/LICENSE
ykbio-1.0.1.dist-info/METADATA
ykbio-1.0.1.dist-info/WHEEL
ykbio-1.0.1.dist-info/top_level.txt
ykbio-1.0.1.dist-info/RECORD
