Metadata-Version: 2.1
Name: ykbio
Version: 1.0.1
Summary: More convenient to process biological data
Home-page: UNKNOWN
Author: yunkai.wang
Author-email: wangyunkai0901@163.com
License: UNKNOWN
Platform: UNKNOWN
Classifier: Programming Language :: Python :: 3
Classifier: License :: OSI Approved :: MIT License
Classifier: Operating System :: OS Independent
Requires-Python: >=3.6
